{
    "Ar36": {
        "error": 0.00039760369439431723,
        "error_type": "SEM",
        "filter_outliers_dict": {
            "filter_outliers": true,
            "iterations": 1,
            "std_devs": 2
        },
        "fit": "Linear",
        "fn": 58,
        "include_baseline_error": false,
        "n": 60,
        "reviewed": true,
        "value": 0.008041033845794063
    },
    "Ar37": {
        "error": 0.012500237025239887,
        "error_type": "SEM",
        "filter_outliers_dict": {
            "filter_outliers": true,
            "iterations": 1,
            "std_devs": 2
        },
        "fit": "Linear",
        "fn": 58,
        "include_baseline_error": false,
        "n": 60,
        "reviewed": true,
        "value": 0.10480852030567542
    },
    "Ar38": {
        "error": 0.011579063892963839,
        "error_type": "SEM",
        "filter_outliers_dict": {
            "filter_outliers": true,
            "iterations": 1,
            "std_devs": 2
        },
        "fit": "Linear",
        "fn": 58,
        "include_baseline_error": false,
        "n": 60,
        "reviewed": true,
        "value": 0.02896270371006448
    },
    "Ar39": {
        "error": 0.020045128070977546,
        "error_type": "SEM",
        "filter_outliers_dict": {
            "filter_outliers": true,
            "iterations": 1,
            "std_devs": 2
        },
        "fit": "Linear",
        "fn": 58,
        "include_baseline_error": false,
        "n": 60,
        "reviewed": true,
        "value": 2.044154508230901
    },
    "Ar40": {
        "error": 0.07785027988734093,
        "error_type": "SEM",
        "filter_outliers_dict": {
            "filter_outliers": true,
            "iterations": 1,
            "std_devs": 2
        },
        "fit": "Linear",
        "fn": 57,
        "include_baseline_error": false,
        "n": 60,
        "reviewed": true,
        "value": 640.3789183397064
    },
    "Ar41": {
        "error": 0.0065804182564677014,
        "error_type": "SEM",
        "filter_outliers_dict": {
            "filter_outliers": true,
            "iterations": 1,
            "std_devs": 2
        },
        "fit": "Average",
        "value": 0.023576778039046602
    }
}